rabs/__init__.py
rabs/main.py
rabs-0.1.0.dist-info/METADATA
rabs-0.1.0.dist-info/WHEEL
rabs-0.1.0.dist-info/RECORD
