Metadata-Version: 2.1
Name: rabs
Version: 0.1.0
Summary: 
Author: bn-l
Requires-Python: >=3.10,<4.0
Classifier: Programming Language :: Python :: 3
Classifier: Programming Language :: Python :: 3.10
Classifier: Programming Language :: Python :: 3.11
Classifier: Programming Language :: Python :: 3.12
